<?xml version="1.0" encoding="utf-8"?>
<odoo >
    
    <!--
        <data noupdate="1">
          <delete model="ir.ui.menu" id="sale.menu_sale_quotations"/>
    </data>

    1) create one file in security folder [security/security.xml​]

    <?xml version="1.0" encoding="utf-8"?>
    <odoo>
        <data noupdate="0">

    <record id="make_invisible" model="res.groups">
        <field name="name">Show Crm Menu</field>
    </record>
    <record model="ir.ui.menu" id="crm.crm_menu_root">
        <field name="groups_id" eval="[(5,ref('make_invisible'))]"/>
    </record>

    </data>


    -->

     <record id="view_order_form_inherit_sale_mobel" model="ir.ui.view">
            <field name="name">sale.order.form.sale.stock</field>
            <field name="model">sale.order</field>
            <field name="inherit_id" ref="sale.view_order_form"/>
            <field name="arch" type="xml">   
                <xpath expr="//page/field[@name='order_line']/tree/field[@name='price_unit']" position="before">            
                    <field name="status_sales_tracking_id" />
                </xpath>                
           </field>
        </record>


   <data>
    <record id="view_order_tree_line_magento" model="ir.ui.view">
        <field name="name">sale.order.tree.lines.magento</field>
        <field name="model">sale.order.line</field>
        <field name="arch" type="xml">
            <tree string="Sales Orders Line Magento" create="0" multi_edit="1" >
                <field name="status_sales_tracking_id" />
                <field name="product_id" options='{"no_create": True}'  />
                <field name="url_prd" options="{'no_create': True}"/>                
                <field name="order_id" optional="hide"/>
                <field name="create_date" />
                <field name="company_id" optional="hide" options="{'no_create': True}" groups="base.group_multi_company"/>
                <field name="order_partner_id" />
                <field name="name" optional="hide"/>
                <field name="price_unit" />                
                <field name="product_uom_qty"/>
                <field name="qty_delivered" optional="hide" />
                <field name="state" optional="hide"/>

            </tree>
        </field>
    </record>


    <record id="view_order_tree_line_magento2" model="ir.ui.view">
        <field name="model">sale.order.line</field>
        <field name="inherit_id" ref="mobel.view_order_tree_line_magento" />
        <field name="arch" type="xml">
             <field name="product_id" position="attributes">
                <attribute name="options">{
               "bg_color": "white; plum: status_sales_tracking_id == 'payment_received'; thistle: status_sales_tracking_id == 'preparend_send_store_miami'; deepskyblue: status_sales_tracking_id == 'on_deposit_miami'; yellowgreen: status_sales_tracking_id == 'traveling_to_uruguay'; palevioletred: status_sales_tracking_id == 'arrived'; yellow: status_sales_tracking_id == 'ready_to_deliver';  white: status_sales_tracking_id == 'delivered';"
      
            }</attribute>
            </field>

            <field name="status_sales_tracking_id" position="attributes">
                <attribute name="options">{
               "bg_color": "white; plum: status_sales_tracking_id == 'payment_received'; thistle: status_sales_tracking_id == 'preparend_send_store_miami'; deepskyblue: status_sales_tracking_id == 'on_deposit_miami'; yellowgreen: status_sales_tracking_id == 'traveling_to_uruguay'; palevioletred: status_sales_tracking_id == 'arrived'; yellow: status_sales_tracking_id == 'ready_to_deliver';  white: status_sales_tracking_id == 'delivered';"
      
            }</attribute>
            </field>

            <field name="url_prd" position="attributes">
                <attribute name="options">{
               "bg_color": "white; plum: status_sales_tracking_id == 'payment_received'; thistle: status_sales_tracking_id == 'preparend_send_store_miami'; deepskyblue: status_sales_tracking_id == 'on_deposit_miami'; yellowgreen: status_sales_tracking_id == 'traveling_to_uruguay'; palevioletred: status_sales_tracking_id == 'arrived'; yellow: status_sales_tracking_id == 'ready_to_deliver';  white: status_sales_tracking_id == 'delivered';"
      
            }</attribute>
            </field>


            <field name="order_id" position="attributes">
                <attribute name="options">{
               "bg_color": "white; plum: status_sales_tracking_id == 'payment_received'; thistle: status_sales_tracking_id == 'preparend_send_store_miami'; deepskyblue: status_sales_tracking_id == 'on_deposit_miami'; yellowgreen: status_sales_tracking_id == 'traveling_to_uruguay'; palevioletred: status_sales_tracking_id == 'arrived'; yellow: status_sales_tracking_id == 'ready_to_deliver';  white: status_sales_tracking_id == 'delivered';"
      
            }</attribute>
            </field>


            <field name="create_date" position="attributes">
                <attribute name="options">{
               "bg_color": "white; plum: status_sales_tracking_id == 'payment_received'; thistle: status_sales_tracking_id == 'preparend_send_store_miami'; deepskyblue: status_sales_tracking_id == 'on_deposit_miami'; yellowgreen: status_sales_tracking_id == 'traveling_to_uruguay'; palevioletred: status_sales_tracking_id == 'arrived'; yellow: status_sales_tracking_id == 'ready_to_deliver';  white: status_sales_tracking_id == 'delivered';"
      
            }</attribute>
            </field>

             <field name="order_partner_id" position="attributes">
                <attribute name="options">{
               "bg_color": "white; plum: status_sales_tracking_id == 'payment_received'; thistle: status_sales_tracking_id == 'preparend_send_store_miami'; deepskyblue: status_sales_tracking_id == 'on_deposit_miami'; yellowgreen: status_sales_tracking_id == 'traveling_to_uruguay'; palevioletred: status_sales_tracking_id == 'arrived'; yellow: status_sales_tracking_id == 'ready_to_deliver';  white: status_sales_tracking_id == 'delivered';"
      
            }</attribute>
            </field>


            <field name="price_unit" position="attributes">
                <attribute name="options">{
               "bg_color": "white; plum: status_sales_tracking_id == 'payment_received'; thistle: status_sales_tracking_id == 'preparend_send_store_miami'; deepskyblue: status_sales_tracking_id == 'on_deposit_miami'; yellowgreen: status_sales_tracking_id == 'traveling_to_uruguay'; palevioletred: status_sales_tracking_id == 'arrived'; yellow: status_sales_tracking_id == 'ready_to_deliver';  white: status_sales_tracking_id == 'delivered';"
      
            }</attribute>
            </field>


            <field name="product_uom_qty" position="attributes">
                <attribute name="options">{
               "bg_color": "white; plum: status_sales_tracking_id == 'payment_received'; thistle: status_sales_tracking_id == 'preparend_send_store_miami'; deepskyblue: status_sales_tracking_id == 'on_deposit_miami'; yellowgreen: status_sales_tracking_id == 'traveling_to_uruguay'; palevioletred: status_sales_tracking_id == 'arrived'; yellow: status_sales_tracking_id == 'ready_to_deliver';  white: status_sales_tracking_id == 'delivered';"
      
            }</attribute>
            </field>
            


        </field>
    </record>

    <record id="sale.action_quotations_with_onboarding" model="ir.actions.act_window">
       <field name="domain">[('purchase_confirmed','=',True)]</field>
    </record>

  


    <record id="sale.action_orders" model="ir.actions.act_window">
       <field name="domain">[('state', 'not in', ('sent', 'cancel'))]</field>
   </record>


    <record id="view_order_tree_2" model="ir.ui.view">
        <field name="name">sale.order.tree.inherit.sale.mobel</field>
        <field name="model">sale.order</field>
        <field name="inherit_id" ref="sale.view_order_tree"/>
        <field name="arch" type="xml">
            <xpath expr="//field[@name='amount_total']" position="after">
                <field name="purchase_confirmed" />
            </xpath>
        </field>
    </record>

    <record id="view_quotation_tree_2" model="ir.ui.view">
        <field name="name">sale.quotation.tree.inherit.sale.mobel</field>
        <field name="model">sale.order</field>
        <field name="inherit_id" ref="sale.view_quotation_tree"/>
        <field name="arch" type="xml">
            <xpath expr="//field[@name='amount_total']" position="after">
                <field name="purchase_confirmed" />
            </xpath>
        </field>
    </record>


    <record id="sale_order_view_search_inherit_quotation_mobel" model="ir.ui.view">
        <field name="name">sale.order.search.inherit.quotation.mobel</field>
        <field name="model">sale.order</field>
        <field name="mode">primary</field>
        <field name="inherit_id" ref="sale.view_sales_order_filter"/>
        <field name="arch" type="xml">
            <xpath expr="//filter[@name='my_sale_orders_filter']" position="before">
                <field name="purchase_confirmed"/>
                <separator/>
                <filter string="Purchase Confirmed" name="purchase_confirmed" domain="[('purchase_confirmed', '=', True)]"/>
                
            </xpath>
        </field>
    </record>


    <record id="action_quotations_with_onboarding_line_magento" model="ir.actions.act_window">
        <field name="name">Ordenes de Venta Magento</field>
        <field name="type">ir.actions.act_window</field>
        <field name="res_model">sale.order.line</field>
        <field name="view_mode">tree,kanban,form,calendar,pivot,graph,activity</field>
        <field name="view_id" ref="mobel.view_order_tree_line_magento"/>
        <field name="domain">[('state_process', 'in', ['initial','not_available'])]</field> 
        <field name="view_mode">tree</field>
        <field name="context">{}</field>
           
    </record>

    <menuitem id="sale_lines_orders_menu" name="Ordenes de Venta Magento" parent="sale.sale_order_menu" sequence="0" action="mobel.action_quotations_with_onboarding_line_magento"/>


     <record id="view_order_tree_line_magento_pending" model="ir.ui.view">
        <field name="name">sale.order.tree.lines.magento</field>
        <field name="model">sale.order.line</field>
        <field name="arch" type="xml">
            <tree string="Sales Orders Line Magento" multi_edit="1" >
                <field name="status_sales_tracking_id" />
                <field name="display_list" />                
                <field name="state_process" />
                <field name="product_id" />
                <field name="url_prd" />                
                <field name="order_id" optional="hide"/>
                <field name="create_date" />
                <field name="company_id" optional="hide" options="{'no_create': True}" groups="base.group_multi_company"/>
                <field name="order_partner_id" />
                <field name="name" optional="hide"/>
                <field name="price_unit" />                
                <field name="product_uom_qty"/>
                <field name="qty_delivered" optional="hide" />
                <field name="status_tracking_id" widget="badge" decoration-success="status_tracking_id == 'Pago Recibido'" decoration-info="status_tracking_id not in ('Pago Recibido')"/>                
                <field name="state" optional="hide"/>

            </tree>
        </field>
    </record>

     <record id="view_order_tree_line_magento_pending2" model="ir.ui.view">
        <field name="model">sale.order.line</field>
        <field name="inherit_id" ref="mobel.view_order_tree_line_magento_pending" />
        <field name="arch" type="xml">
             <field name="product_id" position="attributes">
                <attribute name="options">{
               "bg_color": "white; plum: status_sales_tracking_id == 'payment_received'; thistle: status_sales_tracking_id == 'preparend_send_store_miami'; deepskyblue: status_sales_tracking_id == 'on_deposit_miami'; yellowgreen: status_sales_tracking_id == 'traveling_to_uruguay'; palevioletred: status_sales_tracking_id == 'arrived'; yellow: status_sales_tracking_id == 'ready_to_deliver';  white: status_sales_tracking_id == 'delivered';"
      
            }</attribute>
            </field>

            <field name="status_sales_tracking_id" position="attributes">
                <attribute name="options">{
               "bg_color": "white; plum: status_sales_tracking_id == 'payment_received'; thistle: status_sales_tracking_id == 'preparend_send_store_miami'; deepskyblue: status_sales_tracking_id == 'on_deposit_miami'; yellowgreen: status_sales_tracking_id == 'traveling_to_uruguay'; palevioletred: status_sales_tracking_id == 'arrived'; yellow: status_sales_tracking_id == 'ready_to_deliver';  white: status_sales_tracking_id == 'delivered';"
      
            }</attribute>
            </field>

            <field name="url_prd" position="attributes">
                <attribute name="options">{
               "bg_color": "white; plum: status_sales_tracking_id == 'payment_received'; thistle: status_sales_tracking_id == 'preparend_send_store_miami'; deepskyblue: status_sales_tracking_id == 'on_deposit_miami'; yellowgreen: status_sales_tracking_id == 'traveling_to_uruguay'; palevioletred: status_sales_tracking_id == 'arrived'; yellow: status_sales_tracking_id == 'ready_to_deliver';  white: status_sales_tracking_id == 'delivered';"
      
            }</attribute>
            </field>


            <field name="order_id" position="attributes">
                <attribute name="options">{
               "bg_color": "white; plum: status_sales_tracking_id == 'payment_received'; thistle: status_sales_tracking_id == 'preparend_send_store_miami'; deepskyblue: status_sales_tracking_id == 'on_deposit_miami'; yellowgreen: status_sales_tracking_id == 'traveling_to_uruguay'; palevioletred: status_sales_tracking_id == 'arrived'; yellow: status_sales_tracking_id == 'ready_to_deliver';  white: status_sales_tracking_id == 'delivered';"
      
            }</attribute>
            </field>


            <field name="create_date" position="attributes">
                <attribute name="options">{
               "bg_color": "white; plum: status_sales_tracking_id == 'payment_received'; thistle: status_sales_tracking_id == 'preparend_send_store_miami'; deepskyblue: status_sales_tracking_id == 'on_deposit_miami'; yellowgreen: status_sales_tracking_id == 'traveling_to_uruguay'; palevioletred: status_sales_tracking_id == 'arrived'; yellow: status_sales_tracking_id == 'ready_to_deliver';  white: status_sales_tracking_id == 'delivered';"
      
            }</attribute>
            </field>

             <field name="order_partner_id" position="attributes">
                <attribute name="options">{
               "bg_color": "white; plum: status_sales_tracking_id == 'payment_received'; thistle: status_sales_tracking_id == 'preparend_send_store_miami'; deepskyblue: status_sales_tracking_id == 'on_deposit_miami'; yellowgreen: status_sales_tracking_id == 'traveling_to_uruguay'; palevioletred: status_sales_tracking_id == 'arrived'; yellow: status_sales_tracking_id == 'ready_to_deliver';  white: status_sales_tracking_id == 'delivered';"
      
            }</attribute>
            </field>


            <field name="price_unit" position="attributes">
                <attribute name="options">{
               "bg_color": "white; plum: status_sales_tracking_id == 'payment_received'; thistle: status_sales_tracking_id == 'preparend_send_store_miami'; deepskyblue: status_sales_tracking_id == 'on_deposit_miami'; yellowgreen: status_sales_tracking_id == 'traveling_to_uruguay'; palevioletred: status_sales_tracking_id == 'arrived'; yellow: status_sales_tracking_id == 'ready_to_deliver';  white: status_sales_tracking_id == 'delivered';"
      
            }</attribute>
            </field>


            <field name="product_uom_qty" position="attributes">
                <attribute name="options">{
               "bg_color": "white; plum: status_sales_tracking_id == 'payment_received'; thistle: status_sales_tracking_id == 'preparend_send_store_miami'; deepskyblue: status_sales_tracking_id == 'on_deposit_miami'; yellowgreen: status_sales_tracking_id == 'traveling_to_uruguay'; palevioletred: status_sales_tracking_id == 'arrived'; yellow: status_sales_tracking_id == 'ready_to_deliver';  white: status_sales_tracking_id == 'delivered';"
      
            }</attribute>
            </field>
            


        </field>
    </record>



    <record id="action_quotations_with_onboarding_line_magento_pending" model="ir.actions.act_window">
        <field name="name">Ordenes Pendientes/No disponibles</field>
        <field name="type">ir.actions.act_window</field>
        <field name="res_model">sale.order.line</field>
        <field name="view_mode">tree,kanban,form,calendar,pivot,graph,activity</field>
        <field name="view_id" ref="mobel.view_order_tree_line_magento_pending"/>
        <field name="domain">['&amp;',('state_process', 'in', ['pending']),('display_list','=',False)]</field> 
        <field name="view_mode">tree</field>
        <field name="context">{}</field>
           
    </record>

    <menuitem id="sale_lines_orders_menu_2" name="Ordenes Pendientes/No disponibles" parent="sale.sale_order_menu" sequence="10" action="mobel.action_quotations_with_onboarding_line_magento_pending"/>


    <record id="sales_status_tracking_view_tree" model="ir.ui.view">
        <field name="name">status.tracking.view.tree</field>
        <field name="model">status.tracking</field>
        <field name="arch" type="xml">
            <tree string="Status Tacking" editable="bottom">
                <field name="name"/>
                <field name="color" widget="color_picker" />
            </tree>
        </field>
    </record>

    <record id="sales_status_tracking_action" model="ir.actions.act_window">
        <field name="name">Status Tracking</field>
        <field name="res_model">status.tracking</field>
        <field name="view_id" ref="sales_status_tracking_view_tree"/>
        <field name="help" type="html">
            <p class="o_view_nocontent_smiling_face">
            Create status Tracking for your sales
            </p>
        </field>
    </record>

    <menuitem
        id="menu_status_tracking"
        name="Status Tracking"
        action="mobel.sales_status_tracking_action"
        parent="sale.menu_sales_config"
        sequence="1"/>

</data>
</odoo>
